pyctuator/__init__.py
pyctuator/auth.py
pyctuator/environment/__init__.py
pyctuator/environment/custom_environment_provider.py
pyctuator/environment/environment_provider.py
pyctuator/environment/os_env_variables_impl.py
pyctuator/environment/scrubber.py
pyctuator/health/__init__.py
pyctuator/health/db_health_provider.py
pyctuator/health/diskspace_health_impl.py
pyctuator/health/health_provider.py
pyctuator/health/redis_health_provider.py
pyctuator/httptrace/__init__.py
pyctuator/httptrace/http_header_scrubber.py
pyctuator/httptrace/http_tracer.py
pyctuator/impl/__init__.py
pyctuator/impl/aiohttp_pyctuator.py
pyctuator/impl/fastapi_pyctuator.py
pyctuator/impl/flask_pyctuator.py
pyctuator/impl/pyctuator_impl.py
pyctuator/impl/pyctuator_router.py
pyctuator/impl/spring_boot_admin_registration.py
pyctuator/impl/tornado_pyctuator.py
pyctuator/logfile/logfile.py
pyctuator/logging/__init__.py
pyctuator/logging/pyctuator_logging.py
pyctuator/metrics/__init__.py
pyctuator/metrics/memory_metrics_impl.py
pyctuator/metrics/metrics_provider.py
pyctuator/metrics/thread_metrics_impl.py
pyctuator/py.typed
pyctuator/pyctuator.py
pyctuator/threads/__init__.py
pyctuator/threads/thread_dump_provider.py
pyctuator-1.0.2.dist-info/LICENSE
pyctuator-1.0.2.dist-info/WHEEL
pyctuator-1.0.2.dist-info/METADATA
pyctuator-1.0.2.dist-info/RECORD
